{"ts": 1780856054.9686894, "signals": [{"id": "d6d7faa9-b8a3-4bfa-9a45-eb8cfef95421", "source": "google_trends", "source_id": "iot:student", "source_type": "interest_trend", "title": "Interest trend: student", "content": "Search interest for 'student': latest=52, growth=-28.7%", "url": "https://trends.google.com/trends/explore?q=student", "author": "google_trends", "score": 52, "comments_count": 0, "collected_at": "2026-06-07T18:14:14.967280", "created_at": null, "metadata": {"trend_keyword": "student", "growth_score": -28.7, "category": "interest_trend", "latest_interest": 52, "credibility_score": 0.75}}]}