{"ts": 1780852406.427913, "signals": [{"id": "b33afe28-3ef4-421e-8939-bb55e233c07d", "source": "google_trends", "source_id": "region:productivity:Singapore", "source_type": "regional_interest", "title": "Regional interest: productivity in Singapore", "content": "'productivity' interest in Singapore: score 100", "url": "https://trends.google.com/trends/explore?q=productivity&geo=Singapore", "author": "google_trends", "score": 100, "comments_count": 0, "collected_at": "2026-06-07T17:13:26.427913", "created_at": null, "metadata": {"trend_keyword": "productivity", "region": "Singapore", "growth_score": 100, "category": "regional_interest", "credibility_score": 0.75}}, {"id": "35a26891-bb65-4265-b76e-98d73826409d", "source": "google_trends", "source_id": "region:productivity:American Samoa", "source_type": "regional_interest", "title": "Regional interest: productivity in American Samoa", "content": "'productivity' interest in American Samoa: score 84", "url": "https://trends.google.com/trends/explore?q=productivity&geo=American Samoa", "author": "google_trends", "score": 84, "comments_count": 0, "collected_at": "2026-06-07T17:13:26.427913", "created_at": null, "metadata": {"trend_keyword": "productivity", "region": "American Samoa", "growth_score": 84, "category": "regional_interest", "credibility_score": 0.75}}, {"id": "bb7ea85e-3cd1-46e9-95ab-e0ba6ff194ec", "source": "google_trends", "source_id": "region:productivity:South Korea", "source_type": "regional_interest", "title": "Regional interest: productivity in South Korea", "content": "'productivity' interest in South Korea: score 78", "url": "https://trends.google.com/trends/explore?q=productivity&geo=South Korea", "author": "google_trends", "score": 78, "comments_count": 0, "collected_at": "2026-06-07T17:13:26.427913", "created_at": null, "metadata": {"trend_keyword": "productivity", "region": "South Korea", "growth_score": 78, "category": "regional_interest", "credibility_score": 0.75}}, {"id": "561688f6-a831-40d2-8c9e-16abf0cd5174", "source": "google_trends", "source_id": "region:productivity:Ethiopia", "source_type": "regional_interest", "title": "Regional interest: productivity in Ethiopia", "content": "'productivity' interest in Ethiopia: score 75", "url": "https://trends.google.com/trends/explore?q=productivity&geo=Ethiopia", "author": "google_trends", "score": 75, "comments_count": 0, "collected_at": "2026-06-07T17:13:26.427913", "created_at": null, "metadata": {"trend_keyword": "productivity", "region": "Ethiopia", "growth_score": 75, "category": "regional_interest", "credibility_score": 0.75}}, {"id": "c4c3fc58-8518-49bf-9b4d-f81f980b4f4d", "source": "google_trends", "source_id": "region:productivity:Kosovo", "source_type": "regional_interest", "title": "Regional interest: productivity in Kosovo", "content": "'productivity' interest in Kosovo: score 75", "url": "https://trends.google.com/trends/explore?q=productivity&geo=Kosovo", "author": "google_trends", "score": 75, "comments_count": 0, "collected_at": "2026-06-07T17:13:26.427913", "created_at": null, "metadata": {"trend_keyword": "productivity", "region": "Kosovo", "growth_score": 75, "category": "regional_interest", "credibility_score": 0.75}}]}